odoo/addons/endpoint_route_handler/README.rst
odoo/addons/endpoint_route_handler/__init__.py
odoo/addons/endpoint_route_handler/__manifest__.py
odoo/addons/endpoint_route_handler/exceptions.py
odoo/addons/endpoint_route_handler/post_init_hook.py
odoo/addons/endpoint_route_handler/registry.py
odoo/addons/endpoint_route_handler/controllers/__init__.py
odoo/addons/endpoint_route_handler/controllers/main.py
odoo/addons/endpoint_route_handler/i18n/endpoint_route_handler.pot
odoo/addons/endpoint_route_handler/i18n/it.po
odoo/addons/endpoint_route_handler/migrations/14.0.2.0.0/pre-migrate.py
odoo/addons/endpoint_route_handler/models/__init__.py
odoo/addons/endpoint_route_handler/models/endpoint_route_handler.py
odoo/addons/endpoint_route_handler/models/endpoint_route_handler_tool.py
odoo/addons/endpoint_route_handler/models/endpoint_route_sync_mixin.py
odoo/addons/endpoint_route_handler/models/ir_http.py
odoo/addons/endpoint_route_handler/readme/CONTRIBUTORS.rst
odoo/addons/endpoint_route_handler/readme/DESCRIPTION.rst
odoo/addons/endpoint_route_handler/readme/ROADMAP.rst
odoo/addons/endpoint_route_handler/readme/USAGE.rst
odoo/addons/endpoint_route_handler/security/ir.model.access.csv
odoo/addons/endpoint_route_handler/static/description/icon.png
odoo/addons/endpoint_route_handler/static/description/index.html
odoo/addons/endpoint_route_handler/tests/__init__.py
odoo/addons/endpoint_route_handler/tests/common.py
odoo/addons/endpoint_route_handler/tests/fake_controllers.py
odoo/addons/endpoint_route_handler/tests/test_endpoint.py
odoo/addons/endpoint_route_handler/tests/test_endpoint_controller.py
odoo/addons/endpoint_route_handler/tests/test_registry.py
odoo14_addon_endpoint_route_handler-14.0.2.1.1.dist-info/METADATA
odoo14_addon_endpoint_route_handler-14.0.2.1.1.dist-info/WHEEL
odoo14_addon_endpoint_route_handler-14.0.2.1.1.dist-info/top_level.txt
odoo14_addon_endpoint_route_handler-14.0.2.1.1.dist-info/RECORD
